cmem_plugin_parameters/__init__.py
cmem_plugin_parameters/custom.svg
cmem_plugin_parameters-2.2.0.dist-info/METADATA
cmem_plugin_parameters-2.2.0.dist-info/WHEEL
cmem_plugin_parameters-2.2.0.dist-info/licenses/LICENSE
cmem_plugin_parameters-2.2.0.dist-info/RECORD
