Metadata-Version: 2.4
Name: cmem-plugin-parameters
Version: 2.2.0
Summary: Set or overwrite parameters of a task.
License: Apache-2.0
License-File: LICENSE
Keywords: eccenca Corporate Memory,plugin,yaml,parameters
Author: Thomas Wilmering
Author-email: thomas.wilmering@eccenca.com
Requires-Python: >=3.13,<4.0
Classifier: Development Status :: 4 - Beta
Classifier: Environment :: Plugins
Classifier: License :: OSI Approved :: Apache Software License
Classifier: Programming Language :: Python :: 3
Classifier: Programming Language :: Python :: 3.13
Classifier: Programming Language :: Python :: 3.14
Classifier: Topic :: Software Development :: Libraries :: Python Modules
Requires-Dist: PyYAML (>=6.0,<7.0)
Requires-Dist: cmem-plugin-base (>=4.15.0,<5.0.0)
Project-URL: Homepage, https://github.com/eccenca/cmem-plugin-parameters/
